nova_cli/NOVA_CLI.py
nova_cli/__init__.py
nova_cli/config.py
nova_cli/context.py
nova_cli/convo_history.py
nova_cli/ingest.py
nova_cli/main.py
nova_cli/ml_integration.py
nova_cli/plugin.py
nova_cli/qa_engine.py
nova_cli/setup.py
nova_cli/shared_state.py
nova_cli/startup.py
nova_cli/ML/__init__.py
nova_cli/ML/mlops/__init__.py
nova_cli/ML/mlops/experiment_tracker.py
nova_cli/ML/models/__init__.py
nova_cli/ML/models/advanced_rag.py
nova_cli/ML/models/custom_enbedding.py
nova_cli/ML/models/intent_classifier.py
nova_cli/ML/models/nlp_pipeline.py
nova_cli/ML/monitoring/__init__.py
nova_cli/ML/monitoring/model_monitor.py
nova_cli/ML/training/__init__.py
nova_cli/ML/training/model_trainer.py
nova_cli/src/agents/__init__.py
nova_cli/src/agents/agent_manager.py
nova_cli/src/agents/business_consultant.py
nova_cli/src/agents/career_coach.py
nova_cli/src/agents/coding_agent.py
nova_cli/src/agents/emotional_counselor.py
nova_cli/src/agents/medical_advisor.py
nova_cli/src/agents/techincal_architect.py
nova_cli/src/ai_providers/__init__.py
nova_cli/src/ai_providers/free_api_manager.py
nova_cli/src/api/__init__.py
nova_cli/src/api/main.py
nova_cli/src/api/routes/analytics.py
nova_cli/src/api/routes/chat.py
nova_cli/src/core/__init__.py
nova_cli/src/core/config.py
nova_cli/src/memory/__init__.py
nova_cli/src/memory/sharp_memory.py
nova_cli/src/unique_features/__init__.py
nova_cli/src/unique_features/api_drift_detector.py
nova_cli/src/unique_features/smart_orchestrator.py
nova_cli_ai-3.0.0.dist-info/licenses/LICENSE
nova_cli_ai-3.0.0.dist-info/METADATA
nova_cli_ai-3.0.0.dist-info/WHEEL
nova_cli_ai-3.0.0.dist-info/entry_points.txt
nova_cli_ai-3.0.0.dist-info/top_level.txt
nova_cli_ai-3.0.0.dist-info/RECORD
