Metadata-Version: 2.4
Name: nova-cli-ai
Version: 3.0.0
Summary: 🚀 Advanced AI-Powered CLI Assistant
Author-email: Aryan Kakade <aryankakade143@gmail.com>
License: MIT
Project-URL: Homepage, https://github.com/Aryankakade/NOVA-CLI
Project-URL: Repository, https://github.com/Aryankakade/NOVA-CLI.git
Project-URL: Issues, https://github.com/Aryankakade/NOVA-CLI/issues
Keywords: ai,cli,assistant,chatbot,voice,agents,coding,business,medical
Classifier: Development Status :: 5 - Production/Stable
Classifier: Intended Audience :: Developers
Classifier: License :: OSI Approved :: MIT License
Classifier: Programming Language :: Python :: 3.8
Classifier: Programming Language :: Python :: 3.9
Classifier: Programming Language :: Python :: 3.10
Classifier: Programming Language :: Python :: 3.11
Classifier: Topic :: Software Development :: Libraries :: Python Modules
Classifier: Topic :: System :: Shells
Classifier: Topic :: Scientific/Engineering :: Artificial Intelligence
Requires-Python: >=3.8
License-File: LICENSE
Requires-Dist: textual>=0.40.0
Requires-Dist: rich>=13.0.0
Requires-Dist: requests>=2.28.0
Requires-Dist: python-dotenv>=1.0.0
Requires-Dist: numpy>=1.21.0
Requires-Dist: pandas>=1.3.0
Requires-Dist: colorama>=0.4.4
Requires-Dist: pyttsx3>=2.90
Requires-Dist: SpeechRecognition>=3.10.0
Requires-Dist: azure-cognitiveservices-speech>=1.24.0
Requires-Dist: Pillow>=9.0.0
Requires-Dist: PyPDF2>=3.0.0
Requires-Dist: python-docx>=0.8.11
Requires-Dist: openpyxl>=3.0.9
Requires-Dist: chromadb>=0.4.0
Requires-Dist: langchain-community>=0.0.20
Requires-Dist: sentence-transformers>=2.2.0
Requires-Dist: scikit-learn>=1.0.0
Requires-Dist: torch>=1.12.0
Requires-Dist: transformers>=4.21.0
Dynamic: license-file
